<?xml version="1.0" encoding="utf-8"?>
<search>
  
  
  
  <entry>
    <title>免费静态博客部署平台 -- render</title>
    <link href="/2020/12/09/%E5%85%8D%E8%B4%B9%E9%9D%99%E6%80%81%E5%8D%9A%E5%AE%A2%E9%83%A8%E7%BD%B2%E5%B9%B3%E5%8F%B0-render/"/>
    <url>/2020/12/09/%E5%85%8D%E8%B4%B9%E9%9D%99%E6%80%81%E5%8D%9A%E5%AE%A2%E9%83%A8%E7%BD%B2%E5%B9%B3%E5%8F%B0-render/</url>
    
    <content type="html"><![CDATA[<p>Render.com是一个博客部署平台，因为是国外的一个网站，所以在国内很少人有了解这个静态网站部署平台。大家可能有了解GitHub pages或者Netilify这些网站部署网站，Render就和这些差不多，不过Render部署出来的网站相比前两者的速度在国内访问会比较快。<a id="more"></a></p><p>因为我自己是一个博客迷，但是又不怎么经常写博客。</p><p>主要是我对个人博客的痴迷来自博客的美观和排版所带来的一种新鲜感。</p><p>初识博客是在CSDN这样一个博客社区中，每天都有很多人发布新的文章，有关于技术的、吐槽的、经验分享的、问题总结等等这些。</p><p>那时候好像也没啥感觉对于博客，也就是普普通通创建一个账号，在里面发表一些内容而已。和知乎差不多，后来兴趣过后就没什么特别的感觉了。</p><p>后面接触了一下博客园，这个又让我重新感到新鲜。</p><p>于是我又跑到博客园中创建了一个账号</p><p><img src="https://i.loli.net/2020/12/09/NCvkeL7f2uFmJgt.png" alt="image-2020120913290762"></p><p>其实博客园中的主题并不是很好看，而且由于总总审美问题，博客园我最后还是没有选择折腾它。</p><p>后面在接触GitHub的时候，看了B站程序羊的视频。</p><p>程序羊在他的视频中出了一些关于GitHub托管部署静态博客的一些视频教程，我看着他的教程一步一步地把博客搭建了出来，使用Hexo博客框架搭建地。</p><p>我个人感觉这样的博客才是我真正喜欢的个人博客。</p><p>第一，它免费</p><p>第二，它是一个个人网站，可以公开让别人浏览自己的个人网站</p><p>而且程序羊在视频里讲的一些关于找工作，个人技术博客能让自己的简历加分。</p><p>我想了一想，好像挺不错的！</p><p>一个个人网站，收集自己的学习知识，能让自己成长、收获知识，又能让自己在面试的时候作为一个加分项。</p><p>于是我就疯狂迷恋个人博客了。</p><p>使用GitHub托管hexo博客也是有缺点的，而且这一个缺点一度让我放弃了这样一个个人博客。</p><p>那就是访问速度非常慢！</p><p>一般使用GitHub pages搭建出来的博客，它的域名差不多都是：</p><blockquote><p>XXXXX.github.io</p></blockquote><p>这样一个域名。</p><p>不过访问速度就是太慢了！这个速度问题曾经让我非常抓狂。</p><p>后来我就转向了gitee pages上去部署自己的个人博客。</p><blockquote><p>XXXXX.gitee.io</p></blockquote><p>gitee是一个类似GitHub的一个代码托管平台，它也能托管和部署博客。</p><p>经过一番折腾，我也在gitee上面部署了自己的博客，访问速度也还是顶呱呱的，因为gitee的服务器在国内，所以速度是非常快的。</p><p>但是我个人觉得gitee有两个地方让我有点抓狂。</p><p>第一，普通用户单个git仓库最大好像只有500M的容量</p><p>第二，gitee pages每当你上传到gitee仓库中之后，需要手动到网站中去部署你刚刚发布上去的静态博客更新。</p><p>其实手动更新部署这一点我还是可以忍受的。</p><p>但是git库容量有500M大小的限制就让我感觉有一点点不舒服。</p><p>虽然我几年下来写了上千篇博客文章，可能我的文章容量也没超过500M，但是我还是不喜欢那种有上限的感觉。</p><p>我喜欢说万一超过500M了呢？我又要换地方存储博客了。</p><p>当然假设五年下来，我也是用不到500M的空间大小的。</p><p>不过就是不怎么喜欢这种500M上限的感觉。</p><p>像github有1G的仓库容量，G和M相比起来，1G让我感觉比较踏实。</p><p>反正就是因为各种原因，GitHub pages和gitee pages都没能够让我感到满意。</p><p>不过确实自己要有一种不满足感才能驱使自己去寻找更好的替代方案。</p><p>后来我在网上搜索更好的静态博客部署方案的时候，我发现了Netilify这一个网站部署的一个平台。</p><blockquote><p>Netilify就是获取你的GitHub仓库中的静态资源（HTML)文件，将它部署成网站发送到网络上，而且它还能给你一个二级域名。</p></blockquote><p>不过Netilify的服务器在国外，可能需要一定的上网能力才能打开它的网站。</p><p><img src="https://i.loli.net/2020/12/09/TCcXZ8L1eV6d2JA.png" alt="image-20201209180401994"></p><p><img src="https://i.loli.net/2020/12/09/AxrblzZXioKWfkO.png" alt="image-20201209180455704"></p><p>我的其中一个测试用的博客网站就使用它来部署的</p><blockquote><p><a href="https://nothinglin.netlify.app/">https://nothinglin.netlify.app/</a></p></blockquote><p><img src="https://i.loli.net/2020/12/09/B4OJKXwIUe1kt56.png" alt="image-20201209180556172"></p><p>你们打开我这个测试的博客你们会发现，超级慢！</p><p>如果没有一定的上网能力，在国内打开我的博客会非常慢！</p><p>所以，使用Netilify + GitHub部署博客这个方案我就又暂时放一放了。</p><p>我听说可以提速，但是怎么提速我还没找到相关资料，所以我就暂时放一放。</p><p>那么是不是还有与netilify类似的免费部署平台？</p><p>还有Render、Vercel、surge这三个我目前已知在国内部署、访问速度都非常快的静态网站部署免费平台。</p><p>可能大家会比较熟悉Vercel这个平台，其他的因为都是在国外的，所以在国内比较少人接触或者很少有人介绍它们。</p><p>这一篇博客我主要是介绍Render这个部署平台。</p><p>为什么是Render？</p><p>嘿嘿，也没为什么，只要是Render是我最后发现的一个平台，现在对它的印象还比较深，适合记录一下。</p><p>我个人的博客都主要是使用vercel进行部署的，后面会更详细地介绍vercel的。</p><blockquote><p>官网：<a href="https://render.com/">https://render.com/</a></p></blockquote><p><img src="https://i.loli.net/2020/12/09/OVAilqEFD3ndom5.png" alt="image-20201209181506845"></p><p>可能需要先注册一个账号。</p><p><img src="https://i.loli.net/2020/12/09/tiXV8TdrP1mWLwG.png" alt="image-20201209181549689"></p><p>这个可能需要一定的上网能力才能进入面板中，不过部署的网站在国内的访问速度还可以，它给你生成的二级域名在微信中也是可以访问的。</p><p>这说明这个平台还是比较干净的。</p><p>一般你注册之后它会送你7天的会员时长，过期之后不影响你的静态网站部署。</p><p>感兴趣的话可以仔细阅读一下官网。</p><h3 id="如何部署？"><a href="#如何部署？" class="headerlink" title="如何部署？"></a>如何部署？</h3><p><img src="https://i.loli.net/2020/12/09/mfuKJE8kSxhqHWl.png" alt="image-20201209181846313"></p><p>这是我的github的博客测试的静态资源仓库。</p><p><img src="https://i.loli.net/2020/12/09/V3TfZQhm5udg2FI.png" alt="image-20201209181955528"></p><p><img src="https://i.loli.net/2020/12/09/sHe4ORGaN563tPT.png" alt="image-20201209182031000"></p><p>点击新建一个静态资源网站。</p><p><img src="https://i.loli.net/2020/12/09/lHvRsWfJeyhS8Uo.png" alt="image-20201209182217024"></p><p>点击复制仓库地址</p><p><img src="https://i.loli.net/2020/12/09/h3t6IHJl5BvWbQo.png" alt="image-20201209182253896"></p><p><img src="https://i.loli.net/2020/12/09/zxckHIYj8pyJnW1.png" alt="image-20201209182350905"></p><p><img src="https://i.loli.net/2020/12/09/TlmaAy6cqDfpgRH.png" alt="image-20201209182619695"></p><p><img src="https://i.loli.net/2020/12/09/G8SlIbKf9wjWYQk.png" alt="image-20201209182637928"></p><p>像我这样就表明已经部署成功了。</p><p>上面它会给你你的网站的地址,下面的这个就是我在这里部署的网站地址，你们可以打开来测试访问速度如何。</p><blockquote><p><a href="https://nothing-lin.onrender.com/">https://nothing-lin.onrender.com/</a></p></blockquote><p><img src="https://i.loli.net/2020/12/09/HUQ8EnNxVPISG57.png" alt="image-20201209183010817"></p><p>如果是使用自定义域名的话，后面有需要的话我再补充一下吧。目前它给的二级域名还比较干净，国内很多地方都没有对它进行污染。使用它给的二级域名就很不错了。</p><p>Render的话，每个月有100G的访问流量，对于我们这些做博客来使用的就已经够用了，如果还有需要，自己也可以部署其他的HTML网站到上面。</p><p>总之还是不错的。</p><p>不过我是使用Vercel对我自己的博客进行部署的，因为我发现Vercel比较早，所以我就先使用Vercel了，而且Vercel在国内就可以直接打开进行静态资源的部署。</p><p>好了，今天就暂时分享这么多先。如果喜欢我的话，可以关注公众号。</p><p>我是Nothinglin，苦逼的学生仔。</p><p><img src="https://nothinglin.coding.net/p/picture/d/picture/git/raw/master/2020/11/26/20201126105010.png" alt="image-20201126105007791"></p>]]></content>
    
    
    
    <tags>
      
      <tag>Tools</tag>
      
    </tags>
    
  </entry>
  
  
  
  <entry>
    <title>发现新大陆，开源图表框架--ECharts</title>
    <link href="/2020/11/29/%E5%8F%91%E7%8E%B0%E6%96%B0%E5%A4%A7%E9%99%86%EF%BC%8C%E5%BC%80%E6%BA%90%E5%9B%BE%E8%A1%A8%E6%A1%86%E6%9E%B6-ECharts/"/>
    <url>/2020/11/29/%E5%8F%91%E7%8E%B0%E6%96%B0%E5%A4%A7%E9%99%86%EF%BC%8C%E5%BC%80%E6%BA%90%E5%9B%BE%E8%A1%A8%E6%A1%86%E6%9E%B6-ECharts/</url>
    
    <content type="html"><![CDATA[<p>ECharts是一个开源的JS图表框架，如果熟悉Github的朋友们会对其中的contributions表格不陌生。不知道GitHub是不是用了ECharts制作的贡献值图表，但是可以利用ECharts制作出仿GitHub的贡献值图表。<a id="more"></a></p><h2 id="我是怎么发现ECharts的？"><a href="#我是怎么发现ECharts的？" class="headerlink" title="我是怎么发现ECharts的？"></a>我是怎么发现ECharts的？</h2><p>我最近在研究开发一个web项目，应该有点类似博客系统之类的，可以说是从零开始吧。</p><p>像我这些没见过什么世面的大二仔，面对一个web项目简直是毫无头绪。</p><p>我是上大一买了电脑之后才开始接触程序开发的相关知识，可以说接触面相当小。</p><p>大一的课程只是简单教了一些C++和Java的简单基础知识，其他拓展知识大部分都是靠疫情期间在家里网上冲浪吸收的。</p><p>由于我自己的知识面非常窄，天真的我以为所有程序都是靠开发者一个轮子一个轮子的造。</p><p>比如一个资深的程序员接了一个项目并且在一个月就完成了。</p><p>我会天真的以为他是以超强的编程能力来开发项目的，一开始佩服得我五体投地。</p><p>直到我后来接触到了开发框架，我发现好像如果我的知识面再广一点、动手能力和理解能力再锻炼一下，好像我也能够在一个月之内开发出一个不怎么复杂的项目。</p><p>我后面在面临“重复造轮子”和“改造轮子”之间进行了思考。</p><p>重复造轮子吧，如果自己不是大神，起码要花很多很多时间投入，才能造出一个好的轮子。造轮子的人编程能力是毋庸置疑的，但是需要投入的时间就很让我自己思考。</p><blockquote><p>造轮子是学习所需，改轮子是职业素养</p></blockquote><p>这是师兄们偶尔开玩笑提到。我想了一想好像也挺有道理的。</p><p>一般在学习相关知识的时候，尝试重复造轮子的话，能提高自己对相关编程知识的理解。毕竟学习阶段时间就是多，随便造。</p><p>但是如果是在职场赶项目或者参加比赛之类的，重复造轮子就没什么时间成本了。</p><p>一般情况下，时间都是不充分的，除非自己的编程能力非常强，否则大多情况的人都会选择在GitHub上搜索类似的项目源码来阅读和学习，并且改造它用到自己的项目中去。</p><p>额嗯…跑题了。</p><p>我一开始是想设计一个仿GitHub 的contributions的贡献值表格的。</p><p><img src="https://nothinglin.coding.net/p/picture/d/picture/git/raw/master/2020/11/29/20201129180014.png" alt="image-20201129172124322"></p><p>一开始我是有一点懵懵的。</p><p>我的前端基础知识只学了一点HTML，CSS。我的JS还没接触过。</p><p>这该怎么下手？</p><p>我在<a href="https://codepen.io/">codeopen</a>上搜索了一些相似的demo</p><p><img src="https://nothinglin.coding.net/p/picture/d/picture/git/raw/master/2020/11/29/20201129180018.png" alt="image-20201129172533402"></p><p>我利用这个demo改造成了我想要的样子</p><img src="https://NothingLin.coding.net/p/picture/d/picture/git/raw/master/2020/11/29/20201129180020.png" alt="image-20201129172722832" style="zoom:80%;" /><blockquote><p>这是一个改造轮子的经历。</p></blockquote><p>不过在后面的开发中，如果需要设计各种各样的表格的话，如果还是去codeopen上找demo的话，那么js的整合就比较复杂了。</p><p>如果有像jQuery这样一个JS集成框架来设计表格是最好的。</p><p>正当我今天研究一个Contributions表格源码的时候，我突然发现了什么。</p><p><img src="https://nothinglin.coding.net/p/picture/d/picture/git/raw/master/2020/11/29/20201129180025.png" alt="image-20201129173647496"></p><p>我意外地浏览到这个博客，我发现它的这一个contributions表格挺好的，于是我就去他的GitHub上面查看源码。我把相关的代码提取出来后就像下面这样。</p><p><img src="https://nothinglin.coding.net/p/picture/d/picture/git/raw/master/2020/11/29/20201129180038.png" alt="image-20201129173900013"></p><p>我在研究代码的时候，我像优化到最简，然后再阅读它的代码逻辑。方法类似从codeopen上获取demo然后研究一样。</p><p>我在简化HTML代码之后，就是这样：</p><p><img src="https://nothinglin.coding.net/p/picture/d/picture/git/raw/master/2020/11/29/20201129180042.png" alt="image-20201129174314597"></p><p>它的body代码逻辑和css代码逻辑我基本都理解和弄懂了。</p><p>但是它的JS我却不知道怎么简化，</p><p><img src="https://nothinglin.coding.net/p/picture/d/picture/git/raw/master/2020/11/29/20201129180048.png" alt="image-20201129174459367"></p><p>它的JS代码竟然有5万多行！！</p><p>我在codeopen上找到的demo才几十行，就算你的博客有很多js组件，我猜应该也不用几万行的JS代码吧？</p><p>后来我发现：</p><p><img src="https://nothinglin.coding.net/p/picture/d/picture/git/raw/master/2020/11/29/20201129180102.png" alt="image-20201129174733256"></p><p>echars.min.js这个插件和jQuery的插件有点像。</p><p>于是我就上百度搜了一下Echars这个词。</p><p>果然还有像jQuery这样的使用教程，那么我明白了。Echars这个JS插件是一个表格的开发框架来的。</p><h3 id="Echars表格"><a href="#Echars表格" class="headerlink" title="Echars表格"></a>Echars表格</h3><p><img src="https://nothinglin.coding.net/p/picture/d/picture/git/raw/master/2020/11/29/20201129180106.png" alt="image-20201129174954351"></p><p><img src="https://nothinglin.coding.net/p/picture/d/picture/git/raw/master/2020/11/29/20201129180111.png" alt="image-20201129175042934"></p><p><img src="https://nothinglin.coding.net/p/picture/d/picture/git/raw/master/2020/11/29/20201129180119.png" alt="image-20201129173900013"></p><p>菜鸟教程上有这个教程的：<a href="https://www.runoob.com/echarts/echarts-tutorial.html">点击我</a></p><p>其实说到这里，我就思考：今后我学会了Echarts的使用，那么需要制作表格之类的，我就不需要再重复造轮子了。我可以直接使用Echarts这个开发框架来开发自己想要的表格模板。</p><p>所以说，今天发现Echarts，解决了我制作表格的困惑与困难。我的项目进展也解决了这一个表格制作的问题。</p><p>后面可能我需要安排时间来学习Echarts这表格开发框架了。</p><p>可能后面我学习的时候，会记录自己的学习笔记，等后面再说吧！</p><p>今天就先到这。</p><p>我是Nothinglin，苦逼的学生仔。</p><p><img src="https://nothinglin.coding.net/p/picture/d/picture/git/raw/master/2020/11/26/20201126105010.png" alt="image-20201126105007791"></p>]]></content>
    
    
    
    <tags>
      
      <tag>Tools</tag>
      
    </tags>
    
  </entry>
  
  
  
  <entry>
    <title>我最喜欢的PDF分享网站--MaiPDF</title>
    <link href="/2020/11/28/%E6%88%91%E6%9C%80%E5%96%9C%E6%AC%A2%E7%9A%84PDF%E5%88%86%E4%BA%AB%E7%BD%91%E7%AB%99-MaiPDF/"/>
    <url>/2020/11/28/%E6%88%91%E6%9C%80%E5%96%9C%E6%AC%A2%E7%9A%84PDF%E5%88%86%E4%BA%AB%E7%BD%91%E7%AB%99-MaiPDF/</url>
    
    <content type="html"><![CDATA[<p>MaiPDF是什么？我想大家第一反应就是思考这个问题。<a id="more"></a>我先讲一下我是怎么找到这个网站的吧。</p><h2 id="使用MaiPDF的背景"><a href="#使用MaiPDF的背景" class="headerlink" title="使用MaiPDF的背景"></a>使用MaiPDF的背景</h2><p>最近想要在公众号上分享学习笔记之类的文章，到目前为止一直都在筹备着，做好一切的准备之后才开始公众号笔记分享之路。</p><p>为了能更好地整理文章，我搭建了这一个博客进行文章的分类和整理，同时我也准备了gitbook这一个只是仓库来存放我的笔记文章，或者说高大上一点就是博客笔记。</p><p>现在博客网站也准备好了，学习各种工具和学习资源也都准备好了。</p><p>可是我依然是迟迟没有开始，咋回事呢？</p><p>其实我也有尝试过写笔记，但是进行到一半之后，或者说累到极致的时候我在思考。我这样子把书本的内容先用markdown敲一遍下来先，然后再markdown一遍自己的见解，必要时还要画几张自己理解的图片来辅助说明。前前后后你们猜需要实用多少精力？</p><p>就拿我公众号一开始的线性代数笔记来说吧，光是写“矩阵的秩”这一个概念我就要从早上八点起床一直做到晚上十点多，中间没有休停过，除了洗澡和吃饭之外。</p><p>挖草！妈的十多个小时我才写好一个知识点概念。</p><p>原本我是这样想的，刚好那个学期我们学校也开展了线性代数的课程，我就想不如边学边做笔记，输入和输出相结合，这样的学习效率肯定很高吧？再加上之前刚理解“费曼学习技巧”，挖草！这种学习方式简直帅爆了。</p><p>想搞原创哪有这么容易？</p><p>“矩阵的秩”这一个概念，我看一个小时就能用它来解题了，为什么我非要花十多个小时来整理我对“矩阵的秩”的理解？</p><p>我有一篇线性代数的笔记“矩阵的秩”，文章完成需要哪些步骤？</p><ul><li>手敲一遍知识概念</li><li>手动电脑画图或者手机拍照</li><li>思考知识点，思考如何输出知识点</li><li>使用ppt制作动画演示图</li></ul><p>笔记相当于是现学现做的，可是我又在思考：既然我会这个知识点，只要给我半个小时就能理解，为什么我还要花十多个小时还记录这个知识点呢？</p><p>只记录我会的知识点，我不会的知识点却又没时间去思考、去记录、去写下思考过程。我的大部分时间都花在了手敲课本知识内容上了，那么我思考的时间去哪了？记录下来的简单知识点是不是又能够称之为笔记？</p><p>我个人觉得更像课本的Copy版，看我的笔记和看书没什么区别的，那么我又何必花那么多时间写在电脑上呢？</p><p>我也不虚伪了，一开始就是想写一些这种笔记文章吸吸流量，捞一点粉丝。</p><p>可这种坚持忒痛苦！</p><p>知识没学到，反而思考的时间都没了，粉丝也没赚到多少个，还每天都要花掉我自己十多个小时。</p><p>所以我就在“线性代数笔记系列”的系列文章中到第三章我就停下来了。</p><p>写这种笔记文章，我的思考时间没有了，大部分时间都是在做搬运工，稍微有技术含量的就是作图。虽然是应用到了费曼技巧，但是我这种方式利用费曼技巧却非常低效。别人是口述的，我是敲字的，效率自然是没得比。</p><p>我也停更半年多了，转眼我现在也大二了。</p><p>我不想花太多时间在Copy知识点的行为上，我想有更多时间去思考、去记录自己不会的知识点。</p><p>现在我的心态也平和了许多，半年多的冷静期也过了，我记录笔记也是为了让自己更好地理解，会的知识就不要花太多时间去copy了，要赶紧记录不会的问题并且解决。</p><p>说到这里是不是有点跑题了？说好地是介绍网站的，其实上面的也是为了铺垫这个网站。</p><p>现在我的学习资料基本都在电脑上以pdf的形式存放。</p><p>如果我开展笔记分享系列的文章，我肯定是要记录自己不会的知识点，对这些知识点进行深入的分析，写下自己的思考过程。可是单单分享自己的问题又不成知识系统，只有自己看得明白是哪里的问题，别人怎么看？那么怎么办？</p><p>我给自己的解决方案是这样的：</p><ul><li>以pdf文件代替自己copy的内容，在pdf上用荧光笔记录重点知识点和画出自己的困惑点。</li><li>系统学习完第一章内容，使用pdf编辑工具提取第一章的内容</li><li>在博客中列出自己的困惑点，写下自己的思考过程和解决方案</li><li>在线分享pdf内容</li></ul><p>没看明白？</p><p>我再介绍一边吧。打个比方：</p><p>我在电脑上有《线性代数》这个电子书（PDF），我现在要系统学习第一章。于是我把第一章的内容提取出来，另外形成一个第一章的pdf文件，我在提取出来的文件上做记录，记录自己的困惑点和知识重点。</p><p>然后花时间思考自己的困惑点，全部困惑点解决之后，再把这些困惑点记录下来。</p><p>我想在分享自己的困惑点的同时，我也想分享自己学习的第一章内容，这样好让别人知道我学习线性代数第一章都看的是什么教材内容和记录的知识困惑点在哪里。</p><p>于是我在写完困惑点解题思路之后也要把我学习的第一章pdf文件分享给大家。这样才能对这个知识点有一个系统的学习和系统的了解。</p><p>提取pdf的页面内容和记录困惑点和解决困惑点这些都不难，但是怎样把自己学习的pdf电子书分享给大家在线阅读呢？</p><p>我在网上找了很久，一开始是想把pdf电子书上传到百度文库或者是道客巴巴上的。</p><p>但是他们的阅读体验是真的不好！</p><p>最后我发现了MaiPDF，把要分享的文件上传到它那里，然后获取分享链接分享出去。</p><p>我测试了阅读体验，还不错，不过这个网站分享在线pdf有一个特点就是，它在分享的同时也提供了保护机制，防止你截图。在手机端还好吧，在电脑阅读分享出的pdf后，只要鼠标不在阅读区域，那么内容就会自动消失。</p><h2 id="MaiPDF"><a href="#MaiPDF" class="headerlink" title="MaiPDF"></a>MaiPDF</h2><p><img src="https://nothinglin.coding.net/p/picture/d/picture/git/raw/master/2020/11/29/20201129012638.png" alt="image-20201129010331864"></p><h3 id="1、上传pdf"><a href="#1、上传pdf" class="headerlink" title="1、上传pdf"></a>1、上传pdf</h3><p><img src="https://nothinglin.coding.net/p/picture/d/picture/git/raw/master/2020/11/29/20201129012649.png" alt="image-20201129010443620"></p><h3 id="2、分享设置"><a href="#2、分享设置" class="headerlink" title="2、分享设置"></a>2、分享设置</h3><p><img src="https://nothinglin.coding.net/p/picture/d/picture/git/raw/master/2020/11/29/20201129012654.png" alt="image-20201129010725491"></p><ul><li>可打开的次数是，你可以自定义这个pdf能够被打开几次？当打开的次数用完之后该pdf就会被删除，没用完的情况下可以保存5个月，续期的后下面会讲到。</li><li>可以设置阅读时长。</li><li>点击生成阅读链接</li></ul><h3 id="3、获取分享链接"><a href="#3、获取分享链接" class="headerlink" title="3、获取分享链接"></a>3、获取分享链接</h3><p><img src="https://nothinglin.coding.net/p/picture/d/picture/git/raw/master/2020/11/29/20201129012658.png" alt="image-20201129011150818"></p><ul><li>复制阅读链接就可以直接分享了。</li><li>下面的阅读码和修改码很重要，这是关于你这个文件后期要续期的时候用的，对于重要的文件分享要做好记录，以免后期不能对文件续期。</li></ul><h3 id="4、阅读体验"><a href="#4、阅读体验" class="headerlink" title="4、阅读体验"></a>4、阅读体验</h3><p><img src="https://nothinglin.coding.net/p/picture/d/picture/git/raw/master/2020/11/29/20201129014646.png" alt="image-20201129013449556"></p><h3 id="5、分享的pdf续期"><a href="#5、分享的pdf续期" class="headerlink" title="5、分享的pdf续期"></a>5、分享的pdf续期</h3><p><img src="https://nothinglin.coding.net/p/picture/d/picture/git/raw/master/2020/11/29/20201129014641.png" alt="image-20201129011955985"></p><p>因为上传的文件会自动在5个月之后会被系统删除，所以在过期之前回来续期一次又可以有5个月的保存时间。</p><blockquote><p>注意：新旧阅读码和修改码需要保持一致</p></blockquote><p>这一个网站对于我的笔记分享来说起到一个非常关键的作用，我以后学习就不用copy教材了，直接把教材分享出来，直接记录自己的疑难杂症，我觉得这样更高效，这样配合费曼技巧更合适和更高效。</p><p>好了，今天就暂时分享这么多先。如果喜欢我的话，可以关注公众号。</p><p>我是Nothinglin，苦逼的学生仔。</p><p><img src="https://nothinglin.coding.net/p/picture/d/picture/git/raw/master/2020/11/26/20201126105010.png" alt="image-20201126105007791"></p>]]></content>
    
    
    
    <tags>
      
      <tag>Tools</tag>
      
    </tags>
    
  </entry>
  
  
  
  <entry>
    <title>我最喜欢的markdown编辑器--Typora</title>
    <link href="/2020/11/26/%E6%88%91%E6%9C%80%E5%96%9C%E6%AC%A2%E7%9A%84markdown%E7%BC%96%E8%BE%91%E5%99%A8/"/>
    <url>/2020/11/26/%E6%88%91%E6%9C%80%E5%96%9C%E6%AC%A2%E7%9A%84markdown%E7%BC%96%E8%BE%91%E5%99%A8/</url>
    
    <content type="html"><![CDATA[<p>以前不是很喜欢用typora，虽然第一次发现它的时候感觉挺好用的，但是还是由于一开始对它的不了解而把它搁置下来了。   <a id="more"></a>我那时很迷恋静态博客，感觉很有个性的个人网站，重要的是因为它可以部署到GitHub、gitee、coding上，免费！</p><p>静态博客有一个很重要的特点就是文章是使用markdown语法来写的，我那时候就是搜索markdown编辑搜到typora这个软件的。但是怎么感觉和我印象中的markdown不大一样？这个更像富文本编辑器，由于一开始我就是奔着markdown编辑模式去的，所以在一开始的时候还是挺嫌弃typora的。</p><p>最重要的是那时候typora的主题让我很难受，我去官网主题上看了很多次都没有合适自己的。这样我在编辑的时候由于排版不大美观，我最后准备把它卸载掉的。但是网上各个博主都说typora是最简约和最唯美的markdown编辑，所以我就暂时留着它。主要是我当时是很喜欢标准的markdown那种编辑模式：<code>左边编辑、右边浏览</code>。</p><p><img src="https://nothinglin.coding.net/p/picture/d/picture/git/raw/master/2020/11/26/20201126005331.png" alt="image-20201125233807481"></p><p>而typaro更像一个富文本编辑器：</p><p><img src="https://nothinglin.coding.net/p/picture/d/picture/git/raw/master/2020/11/26/20201126005339.png" alt="image-20201125234312136"></p><p>主要是它的这些文本排版显示看着有一些不舒服，没有写作欲望。<code>（只是我的个人感受）</code></p><p>大概是搁置了半年多吧，没想到偶然地逛了逛官网主题，还想挣扎一下typora，毕竟他也确实有着一些不可被替代地优势。我只是不满意内容排版，其他地大可还好。</p><p>没想到官网又退出了许多新主题，我就逐一地看了一遍。</p><blockquote><p>我特别希望怎样地排版？</p></blockquote><p><img src="https://nothinglin.coding.net/p/picture/d/picture/git/raw/master/2020/11/26/20201126005345.png" alt="image-20201125235102587"></p><p>就是能够有纸张地那种轮廓，好像有一张纸垫在桌子上地那种感觉，而不是白茫茫地一片或者黑漆漆的一片，里面再加一些文本内容。这样看起来总觉得有些不舒服，不知道读者们有没有这种感受。就是最起码要有一种轮廓将文本内容围起来。</p><p>有点抽象？</p><p><img src="https://nothinglin.coding.net/p/picture/d/picture/git/raw/master/2020/11/26/20201126005353.png" alt="image-20201125235620720"></p><p>大概就是这种阅读体验和编辑体验，选择标准的markdown编辑的编辑模式也是因为左边的预览部分能够让自己看着很舒服。</p><p><img src="https://nothinglin.coding.net/p/picture/d/picture/git/raw/master/2020/11/26/20201126005358.png" alt="image-20201126000039006"></p><p>你看，这种编辑的舒适感是不是让你的创作激情四飞？可惜这个是macdown编辑器，需要苹果的mac系统才能运行，我也没发现与之相美观的markdown编辑器，只好长叹息以掩涕兮了。</p><p>不过我在浏览typora主题的过程中，发现了一个主题：</p><p><img src="https://nothinglin.coding.net/p/picture/d/picture/git/raw/master/2020/11/26/20201126005407.png" alt="image-20201126000521176"></p><p>看到明显的纸张轮廓了吗？我想要的就是这种编辑的阅读体验感。</p><p>typora有一个优点就是开源，我们可以自定义修改一下typora编辑器的CSS样式样式就行了。</p><p>给你们看看我修改后的样子：</p><p><img src="https://nothinglin.coding.net/p/picture/d/picture/git/raw/master/2020/11/26/20201126005413.png" alt="image-20201126000846741"></p><p>额嗯…我不知道你们觉得好不好看，不过我感觉我看得挺舒服的，很有写作的欲望！</p><p>这个当然只是本地编辑的阅读样式，提交到博客后就不是这个样式了。不过也不差，博客的主题我也是挺喜欢的。我的编辑风格只要相统一就行了。</p><h2 id="下载Typora"><a href="#下载Typora" class="headerlink" title="下载Typora"></a>下载Typora</h2><p>这个软件是开源的，不收费，如果你是大神的话还可以自定义修改它的样式。设计一套符合自己的主题。</p><p>官网地址：<a href="https://typora.io/">点击我进入官网</a></p><h2 id="下载主题"><a href="#下载主题" class="headerlink" title="下载主题"></a>下载主题</h2><p>主题地址：<a href="http://theme.typora.io/">点击我进入官网主题</a></p><h2 id="说明"><a href="#说明" class="headerlink" title="说明"></a>说明</h2><p>可能你刚下载之后得到typora的样子是长这样的：</p><p><img src="https://nothinglin.coding.net/p/picture/d/picture/git/raw/master/2020/11/26/20201126005422.png" alt="image-20201126001755160"></p><blockquote><p>如何设置为一体化样式？</p></blockquote><p><img src="https://nothinglin.coding.net/p/picture/d/picture/git/raw/master/2020/11/26/20201126005425.gif" alt="semantic演示"></p><blockquote><p>可以在偏好设置中设置为一体化之后会挺美观的，不过这个也挺不错的，你可以了解一下它的编辑功能。</p></blockquote><p><img src="https://nothinglin.coding.net/p/picture/d/picture/git/raw/master/2020/11/26/20201126005444.gif" alt="semantic演示"></p><h2 id="下载主题和配置主题"><a href="#下载主题和配置主题" class="headerlink" title="下载主题和配置主题"></a>下载主题和配置主题</h2><p><img src="https://nothinglin.coding.net/p/picture/d/picture/git/raw/master/2020/11/26/20201126103127.png" alt="image-20201126002940893"></p><p><img src="https://nothinglin.coding.net/p/picture/d/picture/git/raw/master/2020/11/26/20201126005454.png" alt="image-20201126003038671"></p><p><img src="https://nothinglin.coding.net/p/picture/d/picture/git/raw/master/2020/11/26/20201126005459.png" alt="image-20201126003417064"></p><blockquote><p>打开主题文件夹</p></blockquote><p><img src="https://nothinglin.coding.net/p/picture/d/picture/git/raw/master/2020/11/26/20201126005531.png" alt="semantic演示"></p><blockquote><p>直接把那两个文件放入主题文件夹中就行了</p></blockquote><p><img src="https://nothinglin.coding.net/p/picture/d/picture/git/raw/master/2020/11/26/20201126005531.png" alt="image-20201126003743414"></p><img src="https://NothingLin.coding.net/p/picture/d/picture/git/raw/master/2020/11/26/20201126005610.gif" alt="semantic演示" style="zoom: 80%;" /><blockquote><p>默认的主题样式是这样的：</p></blockquote><p><img src="https://nothinglin.coding.net/p/picture/d/picture/git/raw/master/2020/11/26/20201126005604.png" alt="image-20201126000521176"></p><blockquote><p>我不想要这个白色的背景，可以自行准备一张背景图片。该主题中的背景是一张重复网格的背景图片，我们只需要更换一个背景图片就行了。</p></blockquote><p><img src="https://nothinglin.coding.net/p/picture/d/picture/git/raw/master/2020/11/26/20201126005629.gif" alt="semantic演示"></p><blockquote><p>需要说明的是，背景图片是那个名为light_wool.png的图片，只需要上传一张图片，把该图片的名字换成light_wool.png即可，替换掉原来的那张照片。</p></blockquote><p><strong>最终的效果图如下：</strong></p><p><img src="https://nothinglin.coding.net/p/picture/d/picture/git/raw/master/2020/11/26/20201126005643.png" alt="image-20201126004656233"></p><p>其实关于Typora我还有很多其他想要讲的使用技巧，但是我并不想这篇文章的内容太长。我可以考虑一下后面再分享一下我使用typora的一些技巧和心得体会。</p><p>这篇文章暂时就这么多先吧。</p><p>我是NothingLin，苦逼的学生仔。</p><p><strong><em>《2020/11/26》</em></strong></p><p><img src="https://nothinglin.coding.net/p/picture/d/picture/git/raw/master/2020/11/26/20201126105010.png" alt="image-20201126105007791"></p>]]></content>
    
    
    
    <tags>
      
      <tag>Tools</tag>
      
    </tags>
    
  </entry>
  
  
  
  <entry>
    <title>Hello World</title>
    <link href="/2016/06/01/hello-world/"/>
    <url>/2016/06/01/hello-world/</url>
    
    <content type="html"><![CDATA[<p>Welcome to <a href="https://hexo.io/">Hexo</a>! This is your very first post. Check <a href="https://hexo.io/docs/">documentation</a> for more info. If you get any problems when using Hexo, you can find the answer in <a href="https://hexo.io/docs/troubleshooting.html">troubleshooting</a> or you can ask me on <a href="https://github.com/hexojs/hexo/issues">GitHub</a>.</p><a id="more"></a><h2 id="Quick-Start"><a href="#Quick-Start" class="headerlink" title="Quick Start"></a>Quick Start</h2><h3 id="Create-a-new-post"><a href="#Create-a-new-post" class="headerlink" title="Create a new post"></a>Create a new post</h3><div class="code-wrapper"><pre class="line-numbers language-bash" data-language="bash"><code class="language-bash">$ hexo new <span class="token string">"My New Post"</span><span aria-hidden="true" class="line-numbers-rows"><span></span></span></code></pre></div><p>More info: <a href="https://hexo.io/docs/writing.html">Writing</a></p><h3 id="Run-server"><a href="#Run-server" class="headerlink" title="Run server"></a>Run server</h3><div class="code-wrapper"><pre class="line-numbers language-bash" data-language="bash"><code class="language-bash">$ hexo server<span aria-hidden="true" class="line-numbers-rows"><span></span></span></code></pre></div><p>More info: <a href="https://hexo.io/docs/server.html">Server</a></p><h3 id="Generate-static-files"><a href="#Generate-static-files" class="headerlink" title="Generate static files"></a>Generate static files</h3><div class="code-wrapper"><pre class="line-numbers language-bash" data-language="bash"><code class="language-bash">$ hexo generate<span aria-hidden="true" class="line-numbers-rows"><span></span></span></code></pre></div><p>More info: <a href="https://hexo.io/docs/generating.html">Generating</a></p><h3 id="Deploy-to-remote-sites"><a href="#Deploy-to-remote-sites" class="headerlink" title="Deploy to remote sites"></a>Deploy to remote sites</h3><div class="code-wrapper"><pre class="line-numbers language-java" data-language="java"><code class="language-java">$ hexo deploy<span aria-hidden="true" class="line-numbers-rows"><span></span></span></code></pre></div><p>More info: <a href="https://hexo.io/docs/one-command-deployment.html">Deployment</a></p><blockquote><p>嘿嘿，哈哈哈</p></blockquote><p><img src="https://i.loli.net/2020/11/25/uxpOAJy9zT8VdS3.png"></p><p><strong>这是测试粗体字</strong></p><p><a href="%E3%80%82">独大的</a></p><p><img src="D:\工作区\typora截图\f6SlhTvBckL1eOW.png"></p>]]></content>
    
    
    
  </entry>
  
  
  
  
</search>
